<?xml version="1.0" ?>
<Nodes>
    <node id="0" x="15.5" y="3" theta="0" c11="0" c12="0" c13="0" c21="0" c22="0" c23="0" c31="0" c32="0" c33="0" />
    <node id="1" x="9" y="0.6" theta="1.57" c11="0" c12="0" c13="0" c21="0" c22="0" c23="0" c31="0" c32="0" c33="0" />
    <node id="2" x="10.9429" y="0.927831" theta="0.920468" c11="3.51663e-05" c12="4.58768e-05" c13="1.67613e-05" c21="4.58768e-05" c22="6.02607e-05" c23="2.17814e-05" c31="1.67613e-05" c32="2.17814e-05" c33="2.94258e-05" />
    <node id="3" x="10.7271" y="1.08252" theta="-1.05214" c11="9.11416e-06" c12="-1.59434e-05" c13="4.08014e-06" c21="-1.59434e-05" c22="2.79601e-05" c23="-7.13343e-06" c31="4.08014e-06" c32="-7.13343e-06" c33="7.71595e-05" />
    <node id="4" x="8.76639" y="1.39127" theta="0.060594" c11="4.66047e-05" c12="2.82192e-06" c13="-6.45941e-07" c21="2.82192e-06" c22="1.99943e-07" c23="-4.03875e-08" c31="-6.45941e-07" c32="-4.03875e-08" c33="0.000115305" />
    <node id="5" x="4.99815" y="0.527372" theta="-2.27679" c11="7.87234e-06" c12="9.22768e-06" c13="-1.74819e-06" c21="9.22768e-06" c22="1.08365e-05" c23="-2.05006e-06" c31="-1.74819e-06" c32="-2.05006e-06" c33="6.26235e-05" />
    <node id="6" x="9.15268" y="1.19089" theta="2.26381" c11="2.37535e-05" c12="-2.85916e-05" c13="-3.4863e-06" c21="-2.85916e-05" c22="3.44526e-05" c23="4.18591e-06" c31="-3.4863e-06" c32="4.18591e-06" c33="6.99115e-05" />
    <node id="7" x="3.65136" y="0.620333" theta="2.97792" c11="3.49941e-05" c12="-5.76658e-06" c13="1.76854e-06" c21="-5.76658e-06" c22="9.74322e-07" c23="-2.82061e-07" c31="1.76854e-06" c32="-2.82061e-07" c33="8.79585e-05" />
    <node id="8" x="8.33391" y="0.715305" theta="-0.145432" c11="0.000380685" c12="-5.5545e-05" c13="0.000230198" c21="-5.5545e-05" c22="8.16625e-06" c23="-3.35828e-05" c31="0.000230198" c32="-3.35828e-05" c33="0.000275754" />
    <node id="9" x="16.2336" y="2.12594" theta="-1.13763" c11="9.44821e-06" c12="-2.03966e-05" c13="-8.50738e-06" c21="-2.03966e-05" c22="4.41122e-05" c23="1.83939e-05" c31="-8.50738e-06" c32="1.83939e-05" c33="0.000102587" />
    <node id="10" x="8.55074" y="6.46108" theta="0.79969" c11="3.33297e-05" c12="3.42338e-05" c13="-2.29086e-05" c21="3.42338e-05" c22="3.52671e-05" c23="-2.35533e-05" c31="-2.29086e-05" c32="-2.35533e-05" c33="0.000117602" />
    <node id="11" x="0.56059" y="2.04115" theta="-2.02263" c11="5.48817e-06" c12="1.12829e-05" c13="-6.40303e-08" c21="1.12829e-05" c22="2.32768e-05" c23="-1.46918e-07" c31="-6.40303e-08" c32="-1.46918e-07" c33="7.37575e-05" />
    <node id="12" x="12.9498" y="1.4145" theta="1.59434" c11="2.22893e-08" c12="-6.3862e-07" c13="3.25329e-08" c21="-6.3862e-07" c22="2.73201e-05" c23="-1.33157e-06" c31="3.25329e-08" c32="-1.33157e-06" c33="5.31417e-05" />
    <node id="13" x="2.43626" y="1.08718" theta="0.513733" c11="2.18252e-05" c12="1.23072e-05" c13="2.32776e-06" c21="1.23072e-05" c22="6.96162e-06" c23="1.31593e-06" c31="2.32776e-06" c32="1.31593e-06" c33="7.1937e-05" />
    <node id="14" x="0.801489" y="3.30705" theta="0.0299866" c11="1.50829e-05" c12="4.5283e-07" c13="-1.35954e-06" c21="4.5283e-07" c22="1.92135e-08" c23="-3.90903e-08" c31="-1.35954e-06" c32="-3.90903e-08" c33="4.63718e-05" />
    <node id="15" x="15.96" y="4.25918" theta="0.103583" c11="0.00022848" c12="2.37414e-05" c13="-9.5853e-05" c21="2.37414e-05" c22="2.52284e-06" c23="-9.96073e-06" c31="-9.5853e-05" c32="-9.96073e-06" c33="0.000165082" />
    <node id="16" x="7.65499" y="6.28001" theta="-2.94045" c11="8.48875e-05" c12="1.72854e-05" c13="5.2451e-06" c21="1.72854e-05" c22="3.61011e-06" c23="1.13836e-06" c31="5.2451e-06" c32="1.13836e-06" c33="0.000157486" />
    <node id="17" x="3.36683" y="1.103" theta="3.13165" c11="3.08261e-05" c12="-3.03429e-07" c13="1.70421e-06" c21="-3.03429e-07" c22="2.38767e-08" c23="-1.19021e-08" c31="1.70421e-06" c32="-1.19021e-08" c33="0.000108189" />
    <node id="18" x="16.4071" y="3.51459" theta="-1.35368" c11="4.14503e-06" c12="-1.85818e-05" c13="-8.30632e-06" c21="-1.85818e-05" c22="8.42198e-05" c23="3.75545e-05" c31="-8.30632e-06" c32="3.75545e-05" c33="0.000117444" />
    <node id="19" x="0.621987" y="3.18141" theta="2.91576" c11="1.72887e-05" c12="-3.96883e-06" c13="6.52409e-07" c21="-3.96883e-06" c22="9.20252e-07" c23="-1.51452e-07" c31="6.52409e-07" c32="-1.51452e-07" c33="4.44725e-05" />
    <node id="20" x="7.44952" y="0.57342" theta="-2.3179" c11="2.77454e-05" c12="2.99507e-05" c13="4.88225e-06" c21="2.99507e-05" c22="3.23575e-05" c23="5.27077e-06" c31="4.88225e-06" c32="5.27077e-06" c33="0.000104169" />
    <node id="21" x="5.12173" y="6.38264" theta="-0.442633" c11="7.64155e-05" c12="-3.61711e-05" c13="3.30282e-07" c21="-3.61711e-05" c22="1.72697e-05" c23="-2.45464e-07" c31="3.30282e-07" c32="-2.45464e-07" c33="0.000160773" />
    <node id="22" x="5.77585" y="1.35231" theta="2.49201" c11="1.71973e-05" c12="-1.30521e-05" c13="-5.42837e-06" c21="-1.30521e-05" c22="9.93992e-06" c23="4.1273e-06" c31="-5.42837e-06" c32="4.1273e-06" c33="8.97476e-05" />
    <node id="23" x="0.633612" y="2.13306" theta="-2.20669" c11="7.91844e-06" c12="1.0696e-05" c13="-2.75485e-07" c21="1.0696e-05" c22="1.45198e-05" c23="-3.96032e-07" c31="-2.75485e-07" c32="-3.96032e-07" c33="7.44848e-05" />
    <node id="24" x="14.6264" y="1.57629" theta="-0.747768" c11="1.33121e-05" c12="-1.23373e-05" c13="6.85627e-06" c21="-1.23373e-05" c22="1.14714e-05" c23="-6.36392e-06" c31="6.85627e-06" c32="-6.36392e-06" c33="9.34761e-05" />
    <node id="25" x="4.31927" y="0.635682" theta="0.593783" c11="1.52591e-05" c12="1.02851e-05" c13="-1.48975e-05" c21="1.02851e-05" c22="6.96477e-06" c23="-1.00648e-05" c31="-1.48975e-05" c32="-1.00648e-05" c33="7.90546e-05" />
</Nodes>
<Edges>
    <edge startVertexID="2" endVertexID="1" successProb="1" cost="0.10496" />
    <edge startVertexID="1" endVertexID="2" successProb="0.9" cost="0.0671877" />
    <edge startVertexID="3" endVertexID="2" successProb="1" cost="0.0367455" />
    <edge startVertexID="2" endVertexID="3" successProb="1" cost="0.063101" />
    <edge startVertexID="3" endVertexID="1" successProb="1" cost="0.0748314" />
    <edge startVertexID="1" endVertexID="3" successProb="1" cost="0.0632798" />
    <edge startVertexID="4" endVertexID="1" successProb="1" cost="0.0693902" />
    <edge startVertexID="1" endVertexID="4" successProb="1" cost="0.0476478" />
    <edge startVertexID="4" endVertexID="3" successProb="1" cost="0.0628316" />
    <edge startVertexID="3" endVertexID="4" successProb="1" cost="0.104271" />
    <edge startVertexID="4" endVertexID="2" successProb="1" cost="0.0763995" />
    <edge startVertexID="2" endVertexID="4" successProb="1" cost="0.119366" />
    <edge startVertexID="6" endVertexID="1" successProb="1" cost="0.0645199" />
    <edge startVertexID="1" endVertexID="6" successProb="1" cost="0.0242512" />
    <edge startVertexID="6" endVertexID="4" successProb="1" cost="0.0497555" />
    <edge startVertexID="4" endVertexID="6" successProb="1" cost="0.0504644" />
    <edge startVertexID="6" endVertexID="2" successProb="1" cost="0.0878669" />
    <edge startVertexID="2" endVertexID="6" successProb="1" cost="0.0873107" />
    <edge startVertexID="6" endVertexID="3" successProb="1" cost="0.0729483" />
    <edge startVertexID="3" endVertexID="6" successProb="1" cost="0.0670204" />
    <edge startVertexID="8" endVertexID="4" successProb="1" cost="0.0799978" />
    <edge startVertexID="4" endVertexID="8" successProb="1" cost="0.07233" />
    <edge startVertexID="8" endVertexID="1" successProb="1" cost="0.0633279" />
    <edge startVertexID="1" endVertexID="8" successProb="1" cost="0.0946528" />
    <edge startVertexID="8" endVertexID="6" successProb="1" cost="0.0881515" />
    <edge startVertexID="6" endVertexID="8" successProb="1" cost="0.0980855" />
    <edge startVertexID="8" endVertexID="3" successProb="1" cost="0.0989448" />
    <edge startVertexID="3" endVertexID="8" successProb="1" cost="0.130096" />
    <edge startVertexID="8" endVertexID="2" successProb="1" cost="0.106942" />
    <edge startVertexID="2" endVertexID="8" successProb="1" cost="0.157491" />
    <edge startVertexID="9" endVertexID="0" successProb="1" cost="0.0607396" />
    <edge startVertexID="0" endVertexID="9" successProb="1" cost="0.0304905" />
    <edge startVertexID="11" endVertexID="7" successProb="1" cost="0.0879689" />
    <edge startVertexID="7" endVertexID="11" successProb="1" cost="0.0755987" />
    <edge startVertexID="11" endVertexID="5" successProb="0.4" cost="0.107597" />
    <edge startVertexID="5" endVertexID="11" successProb="1" cost="0.110427" />
    <edge startVertexID="12" endVertexID="2" successProb="1" cost="0.103707" />
    <edge startVertexID="2" endVertexID="12" successProb="1" cost="0.0673792" />
    <edge startVertexID="12" endVertexID="3" successProb="1" cost="0.0811606" />
    <edge startVertexID="3" endVertexID="12" successProb="1" cost="0.0745754" />
    <edge startVertexID="12" endVertexID="1" successProb="1" cost="0.11506" />
    <edge startVertexID="1" endVertexID="12" successProb="1" cost="0.106409" />
    <edge startVertexID="12" endVertexID="6" successProb="1" cost="0.109215" />
    <edge startVertexID="6" endVertexID="12" successProb="1" cost="0.119566" />
    <edge startVertexID="12" endVertexID="4" successProb="1" cost="0.141081" />
    <edge startVertexID="4" endVertexID="12" successProb="1" cost="0.11617" />
    <edge startVertexID="13" endVertexID="7" successProb="1" cost="0.0510813" />
    <edge startVertexID="7" endVertexID="13" successProb="1" cost="0.0425443" />
    <edge startVertexID="13" endVertexID="11" successProb="1" cost="0.070837" />
    <edge startVertexID="11" endVertexID="13" successProb="1" cost="0.0620155" />
    <edge startVertexID="14" endVertexID="11" successProb="1" cost="0.0374901" />
    <edge startVertexID="11" endVertexID="14" successProb="1" cost="0.0552224" />
    <edge startVertexID="14" endVertexID="13" successProb="1" cost="0.0545001" />
    <edge startVertexID="13" endVertexID="14" successProb="1" cost="0.0659791" />
    <edge startVertexID="15" endVertexID="0" successProb="1" cost="0.100659" />
    <edge startVertexID="0" endVertexID="15" successProb="1" cost="0.086369" />
    <edge startVertexID="15" endVertexID="9" successProb="1" cost="0.104405" />
    <edge startVertexID="9" endVertexID="15" successProb="1" cost="0.118966" />
    <edge startVertexID="17" endVertexID="7" successProb="1" cost="0.0458535" />
    <edge startVertexID="7" endVertexID="17" successProb="1" cost="0.0285761" />
    <edge startVertexID="17" endVertexID="5" successProb="0.6" cost="0.0747821" />
    <edge startVertexID="5" endVertexID="17" successProb="0.4" cost="0.0578091" />
    <edge startVertexID="17" endVertexID="13" successProb="1" cost="0.0390953" />
    <edge startVertexID="13" endVertexID="17" successProb="1" cost="0.0418205" />
    <edge startVertexID="17" endVertexID="11" successProb="1" cost="0.0655006" />
    <edge startVertexID="11" endVertexID="17" successProb="1" cost="0.0806921" />
    <edge startVertexID="18" endVertexID="9" successProb="1" cost="0.0366514" />
    <edge startVertexID="9" endVertexID="18" successProb="1" cost="0.101204" />
    <edge startVertexID="18" endVertexID="15" successProb="1" cost="0.125148" />
    <edge startVertexID="15" endVertexID="18" successProb="1" cost="0.0651555" />
    <edge startVertexID="18" endVertexID="0" successProb="1" cost="0.058013" />
    <edge startVertexID="0" endVertexID="18" successProb="1" cost="0.0536321" />
    <edge startVertexID="19" endVertexID="14" successProb="1" cost="0.0280553" />
    <edge startVertexID="14" endVertexID="19" successProb="1" cost="0.0317814" />
    <edge startVertexID="19" endVertexID="11" successProb="1" cost="0.035452" />
    <edge startVertexID="11" endVertexID="19" successProb="1" cost="0.0479919" />
    <edge startVertexID="19" endVertexID="13" successProb="1" cost="0.0664948" />
    <edge startVertexID="13" endVertexID="19" successProb="1" cost="0.0610253" />
    <edge startVertexID="20" endVertexID="17" successProb="0.8" cost="0.101874" />
    <edge startVertexID="17" endVertexID="20" successProb="1" cost="0.127897" />
    <edge startVertexID="21" endVertexID="16" successProb="1" cost="0.106818" />
    <edge startVertexID="16" endVertexID="21" successProb="1" cost="0.100918" />
    <edge startVertexID="22" endVertexID="7" successProb="1" cost="0.0657748" />
    <edge startVertexID="7" endVertexID="22" successProb="1" cost="0.0929859" />
    <edge startVertexID="22" endVertexID="20" successProb="1" cost="0.0894683" />
    <edge startVertexID="20" endVertexID="22" successProb="0.7" cost="0.0653897" />
    <edge startVertexID="22" endVertexID="17" successProb="1" cost="0.0599061" />
    <edge startVertexID="17" endVertexID="22" successProb="1" cost="0.0930742" />
    <edge startVertexID="22" endVertexID="6" successProb="1" cost="0.12844" />
    <edge startVertexID="6" endVertexID="22" successProb="1" cost="0.103068" />
    <edge startVertexID="22" endVertexID="1" successProb="1" cost="0.143367" />
    <edge startVertexID="1" endVertexID="22" successProb="1" cost="0.110786" />
    <edge startVertexID="22" endVertexID="8" successProb="1" cost="0.0940184" />
    <edge startVertexID="8" endVertexID="22" successProb="1" cost="0.181016" />
    <edge startVertexID="22" endVertexID="4" successProb="1" cost="0.104943" />
    <edge startVertexID="4" endVertexID="22" successProb="1" cost="0.130642" />
    <edge startVertexID="22" endVertexID="13" successProb="1" cost="0.0865232" />
    <edge startVertexID="13" endVertexID="22" successProb="1" cost="0.084114" />
    <edge startVertexID="23" endVertexID="11" successProb="1" cost="0.009999" />
    <edge startVertexID="11" endVertexID="23" successProb="1" cost="0.009999" />
    <edge startVertexID="23" endVertexID="19" successProb="1" cost="0.0446189" />
    <edge startVertexID="19" endVertexID="23" successProb="1" cost="0.0365465" />
    <edge startVertexID="23" endVertexID="14" successProb="1" cost="0.0508508" />
    <edge startVertexID="14" endVertexID="23" successProb="1" cost="0.0366738" />
    <edge startVertexID="23" endVertexID="17" successProb="1" cost="0.0840339" />
    <edge startVertexID="17" endVertexID="23" successProb="1" cost="0.0663076" />
    <edge startVertexID="23" endVertexID="13" successProb="1" cost="0.0636313" />
    <edge startVertexID="13" endVertexID="23" successProb="1" cost="0.070851" />
    <edge startVertexID="23" endVertexID="7" successProb="1" cost="0.0892888" />
    <edge startVertexID="7" endVertexID="23" successProb="1" cost="0.0756657" />
    <edge startVertexID="23" endVertexID="5" successProb="0.7" cost="0.108615" />
    <edge startVertexID="5" endVertexID="23" successProb="1" cost="0.108142" />
    <edge startVertexID="24" endVertexID="9" successProb="1" cost="0.0578514" />
    <edge startVertexID="9" endVertexID="24" successProb="1" cost="0.0623125" />
    <edge startVertexID="24" endVertexID="12" successProb="1" cost="0.068228" />
    <edge startVertexID="12" endVertexID="24" successProb="1" cost="0.0566418" />
    <edge startVertexID="24" endVertexID="3" successProb="1" cost="0.114605" />
    <edge startVertexID="3" endVertexID="24" successProb="1" cost="0.0978235" />
    <edge startVertexID="24" endVertexID="2" successProb="1" cost="0.133703" />
    <edge startVertexID="2" endVertexID="24" successProb="1" cost="0.103342" />
    <edge startVertexID="25" endVertexID="7" successProb="1" cost="0.0436054" />
    <edge startVertexID="7" endVertexID="25" successProb="1" cost="0.0498736" />
    <edge startVertexID="25" endVertexID="13" successProb="1" cost="0.0732024" />
    <edge startVertexID="13" endVertexID="25" successProb="1" cost="0.0542946" />
    <edge startVertexID="25" endVertexID="5" successProb="0.2" cost="0.0340226" />
    <edge startVertexID="5" endVertexID="25" successProb="1" cost="0.0465328" />
    <edge startVertexID="25" endVertexID="17" successProb="1" cost="0.0510143" />
    <edge startVertexID="17" endVertexID="25" successProb="1" cost="0.0663648" />
    <edge startVertexID="25" endVertexID="22" successProb="1" cost="0.0550467" />
    <edge startVertexID="22" endVertexID="25" successProb="1" cost="0.0671553" />
    <edge startVertexID="25" endVertexID="8" successProb="1" cost="0.088867" />
    <edge startVertexID="8" endVertexID="25" successProb="1" cost="0.203962" />
    <edge startVertexID="25" endVertexID="4" successProb="1" cost="0.104775" />
    <edge startVertexID="4" endVertexID="25" successProb="1" cost="0.161666" />
</Edges>
